productionize/__init__.py
productionize/product.py
productionize/workbench.py
productionize-0.1.0.dist-info/LICENSE
productionize-0.1.0.dist-info/METADATA
productionize-0.1.0.dist-info/WHEEL
productionize-0.1.0.dist-info/top_level.txt
productionize-0.1.0.dist-info/RECORD
