Metadata-Version: 2.1
Name: productionize
Version: 0.1.0
Summary: Lightweight ML Deployment Platform
Home-page: https://github.com/LJStroemsdoerfer/productionize
Author: Lukas Jan Stroemsdoerfer
Author-email: ljstroemsdoerfer@gmail.com
License: MIT
Platform: UNKNOWN
